MANIFEST.in
README.rst
setup.py
drat/__init__.py
drat/analysis.py
drat/app.py
drat/parsers.py
drat.egg-info/PKG-INFO
drat.egg-info/SOURCES.txt
drat.egg-info/dependency_links.txt
drat.egg-info/entry_points.txt
drat.egg-info/not-zip-safe
drat.egg-info/requires.txt
drat.egg-info/top_level.txt
drat/dicts/EN_vocab.txt
drat/dicts/dale_chall.txt