Metadata-Version: 1.1
Name: drat
Version: 0.5.0
Summary: A reading text analysis tool
Home-page: https://github.com/riverrun/drat
Author: David Whitlock
Author-email: alovedalongthe@gmail.com
License: GPLv3
Platform: any
Classifier: Development Status :: 5 - Production/Stable
Classifier: Environment :: Console
Classifier: Intended Audience :: End Users/Desktop
Classifier: Intended Audience :: Developers
Classifier: Intended Audience :: Education
Classifier: License :: OSI Approved :: GNU General Public License v3 (GPLv3)
Classifier: Operating System :: OS Independent
Classifier: Programming Language :: Python
Classifier: Programming Language :: Python :: 2.7
Classifier: Programming Language :: Python :: 3
Classifier: Topic :: Education
Classifier: Topic :: Office/Business
